{
    "special_char": [
     { "char":"A","value":"3"},
     { "char":"B","value":"3"},
     { "char":"C","value":"3"},
     { "char":"D","value":"3"},
     { "char":"E","value":"3"},
     { "char":"F","value":"3"},
     { "char":"G","value":"3"},
     { "char":"H","value":"3"},
     { "char":"I","value":"3"},
     { "char":"J","value":"3"},
     { "char":"K","value":"3"},
     { "char":"L","value":"3"},
     { "char":"M","value":"3"},
     { "char":"N","value":"3"},
     { "char":"O","value":"3"},
     { "char":"P","value":"3"},
     { "char":"Q","value":"3"},
     { "char":"R","value":"3"},
     { "char":"S","value":"3"},
     { "char":"T","value":"2"},
     { "char":"U","value":"2"},
     { "char":"V","value":"2"},
     { "char":"W","value":"1"},
     { "char":"X","value":"2"},
     { "char":"Y","value":"3"},
     { "char":"Z","value":"2"},
     { "char":"a","value":"3"},
     { "char":"b","value":"3"},
     { "char":"c","value":"3"},
     { "char":"d","value":"3"},
     { "char":"e","value":"3"},
     { "char":"f","value":"3"},
     { "char":"g","value":"2"},
     { "char":"h","value":"3"},
     { "char":"i","value":"1"},
     { "char":"j","value":"3"},
     { "char":"k","value":"3"},
     { "char":"l","value":"3"},
     { "char":"m","value":"3"},
     { "char":"n","value":"3"},
     { "char":"o","value":"3"},
     { "char":"p","value":"3"},
     { "char":"q","value":"3"},
     { "char":"r","value":"3"},
     { "char":"s","value":"3"},
     { "char":"t","value":"3"},
     { "char":"u","value":"3"},
     { "char":"v","value":"3"},
     { "char":"w","value":"3"},
     { "char":"x","value":"3"},
     { "char":"y","value":"3"},
     { "char":"z","value":"3"},
     { "char":"(","value":"3"},
     { "char":")","value":"3"},
     { "char":",","value":"3"}

             
 ]
}